.gitignore.txt
DESCRIPTION.txt
LICENSE.txt
MANIFEST.in
README.md
requirements.txt
setup.cfg
setup.py
AI_waiter.egg-info/PKG-INFO
AI_waiter.egg-info/SOURCES.txt
AI_waiter.egg-info/dependency_links.txt
AI_waiter.egg-info/requires.txt
AI_waiter.egg-info/top_level.txt
orders/final_order.csv
orders/full_order.csv
src/__init__.py
src/master.py
src/configs/__init__.py
src/configs/config.py
src/convert_speech/__init__.py
src/convert_speech/record_audio.py
src/convert_speech/record_audio2.py
src/convert_speech/record_interface.py
src/convert_speech/speech_to_text.py
src/convert_text/__init__.py
src/convert_text/get_menu_items.py
src/convert_text/text_to_command.py
src/gui/__init__.py
src/gui/display_window2.py