Metadata-Version: 1.2
Name: AI-waiter
Version: 1.0.3
Summary: Code to read record an order and write to a database
Home-page: https://github.com/AltiusBI/wAIter
Author: Josie Park and 
Author-email: josie.park@altiusdata.com
License: MIT
Platform: UNKNOWN
Requires-Python: <3.7
